{
    "name": "ProjectRena\\Task\\CCPDataTask",
    "line": 16,
    "short_desc": "Class CCPDataTask",
    "long_desc": "",
    "hint": null,
    "tags": {
        "package": [
            [
                "ProjectRena\\Task"
            ]
        ]
    },
    "namespace": "ProjectRena\\Task",
    "file": "\/storage\/www\/projectRenaDocs\/..\/projectRena\/src\/Task\/CCPDataTask.php",
    "hash": "01ecf6df5ec1686bd4c05dc0896151b2d8ba5263",
    "parent": "Cilex\\Command\\Command",
    "modifiers": "Stmt_Class",
    "is_trait": false,
    "is_interface": false,
    "aliases": {
        "Command": "Cilex\\Command\\Command",
        "Lib": "ProjectRena\\Lib",
        "RenaApp": "ProjectRena\\RenaApp",
        "InputInterface": "Symfony\\Component\\Console\\Input\\InputInterface",
        "OutputInterface": "Symfony\\Component\\Console\\Output\\OutputInterface"
    },
    "errors": [],
    "interfaces": [],
    "traits": [],
    "properties": [],
    "methods": [],
    "constants": []
}